ntloss/__init__.py
ntloss/core.py
ntloss/py.typed
ntloss/utils.py
ntloss-0.2.3.dist-info/licenses/LICENSE
ntloss-0.2.3.dist-info/METADATA
ntloss-0.2.3.dist-info/WHEEL
ntloss-0.2.3.dist-info/top_level.txt
ntloss-0.2.3.dist-info/RECORD
