Metadata-Version: 2.4
Name: ntloss
Version: 0.2.3
Summary: Number Token Loss - A regression-alike loss to improve numerical reasoning in language models
Author-email: Jannis Born <jab@zurich.ibm.com>, Lars Pennig <lpennig@t-online.de>, Jonas Zausinger <jonas.zausinger@tum.de>, Sarah de Ruiter <Sarah.Louise.De.Ruiter@ibm.com>
License: MIT
Project-URL: Source code, https://github.com/AI4SD/number-token-loss
Project-URL: Bug Tracker, https://github.com/AI4SD/number-token-loss/issues
Project-URL: Paper, https://arxiv.org/abs/2411.02083
Project-URL: Demo, https://huggingface.co/spaces/jannisborn/NumberTokenLoss
Project-URL: Landing Page, https://tum-ai.github.io/number-token-loss/
Keywords: Machine Learning,Language Models,Number Token Loss,AI4Math,LLM,LLM Training,Reasoning models
Classifier: Development Status :: 4 - Beta
Classifier: Intended Audience :: Developers
Classifier: Intended Audience :: Science/Research
Classifier: License :: OSI Approved :: MIT License
Classifier: Programming Language :: Python :: 3
Classifier: Programming Language :: Python :: 3.10
Classifier: Programming Language :: Python :: 3.11
Classifier: Programming Language :: Python :: 3.12
Classifier: Topic :: Scientific/Engineering :: Artificial Intelligence
Requires-Python: >=3.10
License-File: LICENSE
Requires-Dist: transformers>=4.55.0
Requires-Dist: loguru>=0.7.3
Requires-Dist: torch>=2.7.1
Dynamic: license-file
